m1l0_pipeline/__init__.py
m1l0_pipeline/v1/__init__.py
m1l0_pipeline/v1/pipeline_pb2.py
m1l0_pipeline/v1/pipeline_pb2_grpc.py
m1l0_services/__init__.py
m1l0_services/dataservice/__init__.py
m1l0_services/dataservice/v1/__init__.py
m1l0_services/dataservice/v1/data_service_pb2.py
m1l0_services/dataservice/v1/data_service_pb2_grpc.py
m1l0_services/imagebuilder/__init__.py
m1l0_services/imagebuilder/v1/__init__.py
m1l0_services/imagebuilder/v1/imagebuilder_service_pb2.py
m1l0_services/imagebuilder/v1/imagebuilder_service_pb2_grpc.py
m1l0_protobufs-1.4.0.dist-info/METADATA
m1l0_protobufs-1.4.0.dist-info/WHEEL
m1l0_protobufs-1.4.0.dist-info/top_level.txt
m1l0_protobufs-1.4.0.dist-info/RECORD
