Metadata-Version: 2.1
Name: m1l0-protobufs
Version: 1.4.0
Summary: M1L0 Protobufs
Home-page: https://github.com/m1l0ai
Author: Chee Yeo
Author-email: ckyeo.1@gmail.com
License: MIT
Platform: UNKNOWN
Requires-Dist: grpcio-tools (~=1.37.1)
